LICENSE
MANIFEST.in
README.md
changelog.md
setup.py
hocron/__init__.py
hocron/line_pattern.py
hocron.egg-info/PKG-INFO
hocron.egg-info/SOURCES.txt
hocron.egg-info/dependency_links.txt
hocron.egg-info/top_level.txt
test/test_basic.py
test/test_line_pattern.py
test/data/lidl-receipts/lidl-1.hocr
test/data/lidl-receipts/lidl-2.hocr
test/data/lidl-receipts/lidl-3.hocr