Metadata-Version: 2.1
Name: hocron
Version: 0.3.0
Summary: Provides an API layer over HOCR data format
Home-page: https://github.com/papermerge/hocron
Author: Eugen Ciur
Author-email: eugen@papermerge.com
License: Apache 2.0 License
Keywords: metadata,papermerge,plugin,hocr
Platform: UNKNOWN
Classifier: Programming Language :: Python :: 3
Classifier: License :: OSI Approved :: Apache Software License
Classifier: Operating System :: OS Independent
Requires-Python: >=3.7
